Metadata-Version: 1.0
Name: easy-distribution
Version: 0.1
Summary: A module for creating, modifying, and visualizing Gaussian and Binomial distributions.
Home-page: UNKNOWN
Author: Indra Tanaya
Author-email: aryaindratanaya@gmail.com
License: UNKNOWN
Platform: UNKNOWN
